bradLib/__init__.py
bradLib/bradLib.py
bradLib/errorPropagate.py
bradlib-1.3.0.dist-info/licenses/LICENSE.txt
bradlib-1.3.0.dist-info/METADATA
bradlib-1.3.0.dist-info/WHEEL
bradlib-1.3.0.dist-info/top_level.txt
bradlib-1.3.0.dist-info/RECORD
