Metadata-Version: 2.4
Name: bradLib
Version: 1.3.0
Summary: Bradley Day's personal library
Home-page: https://github.com/BradADDay/bradLib
Author: Bradley Day
License: MIT
Classifier: Programming Language :: Python :: 3
Classifier: Operating System :: OS Independent
Classifier: License :: OSI Approved :: MIT License
License-File: LICENSE.txt
Requires-Dist: matplotlib==3.10.3
Requires-Dist: numpy==2.3.2
Requires-Dist: pandas==2.3.0
Requires-Dist: sympy==1.14.0
Dynamic: author
Dynamic: classifier
Dynamic: description
Dynamic: description-content-type
Dynamic: home-page
Dynamic: license
Dynamic: license-file
Dynamic: requires-dist
Dynamic: summary
